{
  "network": "arterial",
  "sumocfg": "networks/arterial/arterial.sumocfg",
  "net_file": "networks/arterial/arterial.net.xml",
  "seed": 20260520,
  "steps": 600,
  "sample_every": 60,
  "warmup": 60,
  "num_samples": 10,
  "samples": [
    {
      "time": 61.0,
      "queues": {
        "C12C2": 0.0,
        "C12N1": 0.0,
        "C12S1": 0.0,
        "C12W_in": 0.0,
        "C22C1": 1.0,
        "C22C3": 0.0,
        "C22N2": 0.0,
        "C22S2": 0.0,
        "C32C2": 0.0,
        "C32C4": 0.0,
        "C32N3": 0.0,
        "C32S3": 0.0,
        "C42C3": 0.0,
        "C42C5": 1.0,
        "C42N4": 0.0,
        "C42S4": 0.0,
        "C52C4": 1.0,
        "C52E_out": 0.0,
        "C52N5": 0.0,
        "C52S5": 0.0,
        "E_out2C5": 1.0,
        "N12C1": 0.0,
        "N22C2": 0.0,
        "N32C3": 1.0,
        "N42C4": 0.0,
        "N52C5": 0.0,
        "S12C1": 0.0,
        "S22C2": 1.0,
        "S32C3": 1.0,
        "S42C4": 1.0,
        "S52C5": 1.0,
        "W_in2C1": 0.0
      },
      "vehicle_counts": {
        "C12C2": 11.0,
        "C12N1": 4.0,
        "C12S1": 2.0,
        "C12W_in": 5.0,
        "C22C1": 13.0,
        "C22C3": 9.0,
        "C22N2": 2.0,
        "C22S2": 4.0,
        "C32C2": 11.0,
        "C32C4": 12.0,
        "C32N3": 3.0,
        "C32S3": 2.0,
        "C42C3": 13.0,
        "C42C5": 11.0,
        "C42N4": 2.0,
        "C42S4": 3.0,
        "C52C4": 13.0,
        "C52E_out": 7.0,
        "C52N5": 2.0,
        "C52S5": 3.0,
        "E_out2C5": 6.0,
        "N12C1": 4.0,
        "N22C2": 4.0,
        "N32C3": 4.0,
        "N42C4": 4.0,
        "N52C5": 4.0,
        "S12C1": 4.0,
        "S22C2": 4.0,
        "S32C3": 4.0,
        "S42C4": 4.0,
        "S52C5": 4.0,
        "W_in2C1": 5.0
      },
      "capacities": {
        "C12C2": 109.12000000000002,
        "C12N1": 114.55999999999999,
        "C12S1": 114.55999999999999,
        "C12W_in": 114.55999999999999,
        "C22C1": 109.12000000000002,
        "C22C3": 109.12000000000002,
        "C22N2": 114.55999999999999,
        "C22S2": 114.55999999999999,
        "C32C2": 109.12000000000002,
        "C32C4": 109.12000000000002,
        "C32N3": 114.55999999999999,
        "C32S3": 114.55999999999999,
        "C42C3": 109.12000000000002,
        "C42C5": 109.12000000000002,
        "C42N4": 114.55999999999999,
        "C42S4": 114.55999999999999,
        "C52C4": 109.12000000000002,
        "C52E_out": 114.55999999999999,
        "C52N5": 114.55999999999999,
        "C52S5": 114.55999999999999,
        "E_out2C5": 114.55999999999999,
        "N12C1": 114.55999999999999,
        "N22C2": 114.55999999999999,
        "N32C3": 114.55999999999999,
        "N42C4": 114.55999999999999,
        "N52C5": 114.55999999999999,
        "S12C1": 114.55999999999999,
        "S22C2": 114.55999999999999,
        "S32C3": 114.55999999999999,
        "S42C4": 114.55999999999999,
        "S52C5": 114.55999999999999,
        "W_in2C1": 114.55999999999999
      },
      "tls_movements": {
        "C2": [
          [
            "C12C2",
            "C22C3"
          ],
          [
            "C12C2",
            "C22N2"
          ],
          [
            "C12C2",
            "C22S2"
          ],
          [
            "C32C2",
            "C22C1"
          ],
          [
            "C32C2",
            "C22N2"
          ],
          [
            "C32C2",
            "C22S2"
          ],
          [
            "N22C2",
            "C22C1"
          ],
          [
            "N22C2",
            "C22C3"
          ],
          [
            "N22C2",
            "C22S2"
          ],
          [
            "S22C2",
            "C22C1"
          ],
          [
            "S22C2",
            "C22C3"
          ],
          [
            "S22C2",
            "C22N2"
          ]
        ],
        "C1": [
          [
            "C22C1",
            "C12N1"
          ],
          [
            "C22C1",
            "C12S1"
          ],
          [
            "C22C1",
            "C12W_in"
          ],
          [
            "N12C1",
            "C12C2"
          ],
          [
            "N12C1",
            "C12S1"
          ],
          [
            "N12C1",
            "C12W_in"
          ],
          [
            "S12C1",
            "C12C2"
          ],
          [
            "S12C1",
            "C12N1"
          ],
          [
            "S12C1",
            "C12W_in"
          ],
          [
            "W_in2C1",
            "C12C2"
          ],
          [
            "W_in2C1",
            "C12N1"
          ],
          [
            "W_in2C1",
            "C12S1"
          ]
        ],
        "C3": [
          [
            "C22C3",
            "C32C4"
          ],
          [
            "C22C3",
            "C32N3"
          ],
          [
            "C22C3",
            "C32S3"
          ],
          [
            "C42C3",
            "C32C2"
          ],
          [
            "C42C3",
            "C32N3"
          ],
          [
            "C42C3",
            "C32S3"
          ],
          [
            "N32C3",
            "C32C2"
          ],
          [
            "N32C3",
            "C32C4"
          ],
          [
            "N32C3",
            "C32S3"
          ],
          [
            "S32C3",
            "C32C2"
          ],
          [
            "S32C3",
            "C32C4"
          ],
          [
            "S32C3",
            "C32N3"
          ]
        ],
        "C4": [
          [
            "C32C4",
            "C42C5"
          ],
          [
            "C32C4",
            "C42N4"
          ],
          [
            "C32C4",
            "C42S4"
          ],
          [
            "C52C4",
            "C42C3"
          ],
          [
            "C52C4",
            "C42N4"
          ],
          [
            "C52C4",
            "C42S4"
          ],
          [
            "N42C4",
            "C42C3"
          ],
          [
            "N42C4",
            "C42C5"
          ],
          [
            "N42C4",
            "C42S4"
          ],
          [
            "S42C4",
            "C42C3"
          ],
          [
            "S42C4",
            "C42C5"
          ],
          [
            "S42C4",
            "C42N4"
          ]
        ],
        "C5": [
          [
            "C42C5",
            "C52E_out"
          ],
          [
            "C42C5",
            "C52N5"
          ],
          [
            "C42C5",
            "C52S5"
          ],
          [
            "E_out2C5",
            "C52C4"
          ],
          [
            "E_out2C5",
            "C52N5"
          ],
          [
            "E_out2C5",
            "C52S5"
          ],
          [
            "N52C5",
            "C52C4"
          ],
          [
            "N52C5",
            "C52E_out"
          ],
          [
            "N52C5",
            "C52S5"
          ],
          [
            "S52C5",
            "C52C4"
          ],
          [
            "S52C5",
            "C52E_out"
          ],
          [
            "S52C5",
            "C52N5"
          ]
        ]
      }
    },
    {
      "time": 121.0,
      "queues": {
        "C12C2": 12.0,
        "C12N1": 0.0,
        "C12S1": 0.0,
        "C12W_in": 0.0,
        "C22C1": 9.0,
        "C22C3": 15.0,
        "C22N2": 0.0,
        "C22S2": 0.0,
        "C32C2": 9.0,
        "C32C4": 12.0,
        "C32N3": 0.0,
        "C32S3": 0.0,
        "C42C3": 10.0,
        "C42C5": 8.0,
        "C42N4": 0.0,
        "C42S4": 0.0,
        "C52C4": 12.0,
        "C52E_out": 0.0,
        "C52N5": 0.0,
        "C52S5": 0.0,
        "E_out2C5": 6.0,
        "N12C1": 0.0,
        "N22C2": 0.0,
        "N32C3": 0.0,
        "N42C4": 0.0,
        "N52C5": 0.0,
        "S12C1": 0.0,
        "S22C2": 0.0,
        "S32C3": 0.0,
        "S42C4": 0.0,
        "S52C5": 0.0,
        "W_in2C1": 7.0
      },
      "vehicle_counts": {
        "C12C2": 19.0,
        "C12N1": 1.0,
        "C12S1": 2.0,
        "C12W_in": 1.0,
        "C22C1": 13.0,
        "C22C3": 20.0,
        "C22N2": 2.0,
        "C22S2": 1.0,
        "C32C2": 15.0,
        "C32C4": 18.0,
        "C32N3": 1.0,
        "C32S3": 1.0,
        "C42C3": 15.0,
        "C42C5": 15.0,
        "C42N4": 0.0,
        "C42S4": 2.0,
        "C52C4": 16.0,
        "C52E_out": 1.0,
        "C52N5": 1.0,
        "C52S5": 1.0,
        "E_out2C5": 12.0,
        "N12C1": 2.0,
        "N22C2": 4.0,
        "N32C3": 4.0,
        "N42C4": 4.0,
        "N52C5": 4.0,
        "S12C1": 4.0,
        "S22C2": 4.0,
        "S32C3": 4.0,
        "S42C4": 4.0,
        "S52C5": 4.0,
        "W_in2C1": 12.0
      },
      "capacities": {
        "C12C2": 109.12000000000002,
        "C12N1": 114.55999999999999,
        "C12S1": 114.55999999999999,
        "C12W_in": 114.55999999999999,
        "C22C1": 109.12000000000002,
        "C22C3": 109.12000000000002,
        "C22N2": 114.55999999999999,
        "C22S2": 114.55999999999999,
        "C32C2": 109.12000000000002,
        "C32C4": 109.12000000000002,
        "C32N3": 114.55999999999999,
        "C32S3": 114.55999999999999,
        "C42C3": 109.12000000000002,
        "C42C5": 109.12000000000002,
        "C42N4": 114.55999999999999,
        "C42S4": 114.55999999999999,
        "C52C4": 109.12000000000002,
        "C52E_out": 114.55999999999999,
        "C52N5": 114.55999999999999,
        "C52S5": 114.55999999999999,
        "E_out2C5": 114.55999999999999,
        "N12C1": 114.55999999999999,
        "N22C2": 114.55999999999999,
        "N32C3": 114.55999999999999,
        "N42C4": 114.55999999999999,
        "N52C5": 114.55999999999999,
        "S12C1": 114.55999999999999,
        "S22C2": 114.55999999999999,
        "S32C3": 114.55999999999999,
        "S42C4": 114.55999999999999,
        "S52C5": 114.55999999999999,
        "W_in2C1": 114.55999999999999
      },
      "tls_movements": {
        "C2": [
          [
            "C12C2",
            "C22C3"
          ],
          [
            "C12C2",
            "C22N2"
          ],
          [
            "C12C2",
            "C22S2"
          ],
          [
            "C32C2",
            "C22C1"
          ],
          [
            "C32C2",
            "C22N2"
          ],
          [
            "C32C2",
            "C22S2"
          ],
          [
            "N22C2",
            "C22C1"
          ],
          [
            "N22C2",
            "C22C3"
          ],
          [
            "N22C2",
            "C22S2"
          ],
          [
            "S22C2",
            "C22C1"
          ],
          [
            "S22C2",
            "C22C3"
          ],
          [
            "S22C2",
            "C22N2"
          ]
        ],
        "C1": [
          [
            "C22C1",
            "C12N1"
          ],
          [
            "C22C1",
            "C12S1"
          ],
          [
            "C22C1",
            "C12W_in"
          ],
          [
            "N12C1",
            "C12C2"
          ],
          [
            "N12C1",
            "C12S1"
          ],
          [
            "N12C1",
            "C12W_in"
          ],
          [
            "S12C1",
            "C12C2"
          ],
          [
            "S12C1",
            "C12N1"
          ],
          [
            "S12C1",
            "C12W_in"
          ],
          [
            "W_in2C1",
            "C12C2"
          ],
          [
            "W_in2C1",
            "C12N1"
          ],
          [
            "W_in2C1",
            "C12S1"
          ]
        ],
        "C3": [
          [
            "C22C3",
            "C32C4"
          ],
          [
            "C22C3",
            "C32N3"
          ],
          [
            "C22C3",
            "C32S3"
          ],
          [
            "C42C3",
            "C32C2"
          ],
          [
            "C42C3",
            "C32N3"
          ],
          [
            "C42C3",
            "C32S3"
          ],
          [
            "N32C3",
            "C32C2"
          ],
          [
            "N32C3",
            "C32C4"
          ],
          [
            "N32C3",
            "C32S3"
          ],
          [
            "S32C3",
            "C32C2"
          ],
          [
            "S32C3",
            "C32C4"
          ],
          [
            "S32C3",
            "C32N3"
          ]
        ],
        "C4": [
          [
            "C32C4",
            "C42C5"
          ],
          [
            "C32C4",
            "C42N4"
          ],
          [
            "C32C4",
            "C42S4"
          ],
          [
            "C52C4",
            "C42C3"
          ],
          [
            "C52C4",
            "C42N4"
          ],
          [
            "C52C4",
            "C42S4"
          ],
          [
            "N42C4",
            "C42C3"
          ],
          [
            "N42C4",
            "C42C5"
          ],
          [
            "N42C4",
            "C42S4"
          ],
          [
            "S42C4",
            "C42C3"
          ],
          [
            "S42C4",
            "C42C5"
          ],
          [
            "S42C4",
            "C42N4"
          ]
        ],
        "C5": [
          [
            "C42C5",
            "C52E_out"
          ],
          [
            "C42C5",
            "C52N5"
          ],
          [
            "C42C5",
            "C52S5"
          ],
          [
            "E_out2C5",
            "C52C4"
          ],
          [
            "E_out2C5",
            "C52N5"
          ],
          [
            "E_out2C5",
            "C52S5"
          ],
          [
            "N52C5",
            "C52C4"
          ],
          [
            "N52C5",
            "C52E_out"
          ],
          [
            "N52C5",
            "C52S5"
          ],
          [
            "S52C5",
            "C52C4"
          ],
          [
            "S52C5",
            "C52E_out"
          ],
          [
            "S52C5",
            "C52N5"
          ]
        ]
      }
    },
    {
      "time": 181.0,
      "queues": {
        "C12C2": 1.0,
        "C12N1": 0.0,
        "C12S1": 0.0,
        "C12W_in": 0.0,
        "C22C1": 1.0,
        "C22C3": 2.0,
        "C22N2": 0.0,
        "C22S2": 0.0,
        "C32C2": 2.0,
        "C32C4": 2.0,
        "C32N3": 0.0,
        "C32S3": 0.0,
        "C42C3": 1.0,
        "C42C5": 0.0,
        "C42N4": 0.0,
        "C42S4": 0.0,
        "C52C4": 0.0,
        "C52E_out": 0.0,
        "C52N5": 0.0,
        "C52S5": 0.0,
        "E_out2C5": 0.0,
        "N12C1": 1.0,
        "N22C2": 1.0,
        "N32C3": 1.0,
        "N42C4": 1.0,
        "N52C5": 1.0,
        "S12C1": 1.0,
        "S22C2": 1.0,
        "S32C3": 1.0,
        "S42C4": 1.0,
        "S52C5": 1.0,
        "W_in2C1": 1.0
      },
      "vehicle_counts": {
        "C12C2": 12.0,
        "C12N1": 1.0,
        "C12S1": 2.0,
        "C12W_in": 2.0,
        "C22C1": 10.0,
        "C22C3": 15.0,
        "C22N2": 3.0,
        "C22S2": 3.0,
        "C32C2": 10.0,
        "C32C4": 10.0,
        "C32N3": 1.0,
        "C32S3": 3.0,
        "C42C3": 11.0,
        "C42C5": 12.0,
        "C42N4": 3.0,
        "C42S4": 2.0,
        "C52C4": 9.0,
        "C52E_out": 2.0,
        "C52N5": 3.0,
        "C52S5": 3.0,
        "E_out2C5": 6.0,
        "N12C1": 5.0,
        "N22C2": 5.0,
        "N32C3": 4.0,
        "N42C4": 5.0,
        "N52C5": 5.0,
        "S12C1": 4.0,
        "S22C2": 4.0,
        "S32C3": 4.0,
        "S42C4": 4.0,
        "S52C5": 5.0,
        "W_in2C1": 7.0
      },
      "capacities": {
        "C12C2": 109.12000000000002,
        "C12N1": 114.55999999999999,
        "C12S1": 114.55999999999999,
        "C12W_in": 114.55999999999999,
        "C22C1": 109.12000000000002,
        "C22C3": 109.12000000000002,
        "C22N2": 114.55999999999999,
        "C22S2": 114.55999999999999,
        "C32C2": 109.12000000000002,
        "C32C4": 109.12000000000002,
        "C32N3": 114.55999999999999,
        "C32S3": 114.55999999999999,
        "C42C3": 109.12000000000002,
        "C42C5": 109.12000000000002,
        "C42N4": 114.55999999999999,
        "C42S4": 114.55999999999999,
        "C52C4": 109.12000000000002,
        "C52E_out": 114.55999999999999,
        "C52N5": 114.55999999999999,
        "C52S5": 114.55999999999999,
        "E_out2C5": 114.55999999999999,
        "N12C1": 114.55999999999999,
        "N22C2": 114.55999999999999,
        "N32C3": 114.55999999999999,
        "N42C4": 114.55999999999999,
        "N52C5": 114.55999999999999,
        "S12C1": 114.55999999999999,
        "S22C2": 114.55999999999999,
        "S32C3": 114.55999999999999,
        "S42C4": 114.55999999999999,
        "S52C5": 114.55999999999999,
        "W_in2C1": 114.55999999999999
      },
      "tls_movements": {
        "C2": [
          [
            "C12C2",
            "C22C3"
          ],
          [
            "C12C2",
            "C22N2"
          ],
          [
            "C12C2",
            "C22S2"
          ],
          [
            "C32C2",
            "C22C1"
          ],
          [
            "C32C2",
            "C22N2"
          ],
          [
            "C32C2",
            "C22S2"
          ],
          [
            "N22C2",
            "C22C1"
          ],
          [
            "N22C2",
            "C22C3"
          ],
          [
            "N22C2",
            "C22S2"
          ],
          [
            "S22C2",
            "C22C1"
          ],
          [
            "S22C2",
            "C22C3"
          ],
          [
            "S22C2",
            "C22N2"
          ]
        ],
        "C1": [
          [
            "C22C1",
            "C12N1"
          ],
          [
            "C22C1",
            "C12S1"
          ],
          [
            "C22C1",
            "C12W_in"
          ],
          [
            "N12C1",
            "C12C2"
          ],
          [
            "N12C1",
            "C12S1"
          ],
          [
            "N12C1",
            "C12W_in"
          ],
          [
            "S12C1",
            "C12C2"
          ],
          [
            "S12C1",
            "C12N1"
          ],
          [
            "S12C1",
            "C12W_in"
          ],
          [
            "W_in2C1",
            "C12C2"
          ],
          [
            "W_in2C1",
            "C12N1"
          ],
          [
            "W_in2C1",
            "C12S1"
          ]
        ],
        "C3": [
          [
            "C22C3",
            "C32C4"
          ],
          [
            "C22C3",
            "C32N3"
          ],
          [
            "C22C3",
            "C32S3"
          ],
          [
            "C42C3",
            "C32C2"
          ],
          [
            "C42C3",
            "C32N3"
          ],
          [
            "C42C3",
            "C32S3"
          ],
          [
            "N32C3",
            "C32C2"
          ],
          [
            "N32C3",
            "C32C4"
          ],
          [
            "N32C3",
            "C32S3"
          ],
          [
            "S32C3",
            "C32C2"
          ],
          [
            "S32C3",
            "C32C4"
          ],
          [
            "S32C3",
            "C32N3"
          ]
        ],
        "C4": [
          [
            "C32C4",
            "C42C5"
          ],
          [
            "C32C4",
            "C42N4"
          ],
          [
            "C32C4",
            "C42S4"
          ],
          [
            "C52C4",
            "C42C3"
          ],
          [
            "C52C4",
            "C42N4"
          ],
          [
            "C52C4",
            "C42S4"
          ],
          [
            "N42C4",
            "C42C3"
          ],
          [
            "N42C4",
            "C42C5"
          ],
          [
            "N42C4",
            "C42S4"
          ],
          [
            "S42C4",
            "C42C3"
          ],
          [
            "S42C4",
            "C42C5"
          ],
          [
            "S42C4",
            "C42N4"
          ]
        ],
        "C5": [
          [
            "C42C5",
            "C52E_out"
          ],
          [
            "C42C5",
            "C52N5"
          ],
          [
            "C42C5",
            "C52S5"
          ],
          [
            "E_out2C5",
            "C52C4"
          ],
          [
            "E_out2C5",
            "C52N5"
          ],
          [
            "E_out2C5",
            "C52S5"
          ],
          [
            "N52C5",
            "C52C4"
          ],
          [
            "N52C5",
            "C52E_out"
          ],
          [
            "N52C5",
            "C52S5"
          ],
          [
            "S52C5",
            "C52C4"
          ],
          [
            "S52C5",
            "C52E_out"
          ],
          [
            "S52C5",
            "C52N5"
          ]
        ]
      }
    },
    {
      "time": 241.0,
      "queues": {
        "C12C2": 6.0,
        "C12N1": 0.0,
        "C12S1": 0.0,
        "C12W_in": 0.0,
        "C22C1": 6.0,
        "C22C3": 7.0,
        "C22N2": 0.0,
        "C22S2": 0.0,
        "C32C2": 4.0,
        "C32C4": 6.0,
        "C32N3": 0.0,
        "C32S3": 0.0,
        "C42C3": 2.0,
        "C42C5": 7.0,
        "C42N4": 0.0,
        "C42S4": 0.0,
        "C52C4": 3.0,
        "C52E_out": 0.0,
        "C52N5": 0.0,
        "C52S5": 0.0,
        "E_out2C5": 0.0,
        "N12C1": 0.0,
        "N22C2": 1.0,
        "N32C3": 0.0,
        "N42C4": 1.0,
        "N52C5": 1.0,
        "S12C1": 1.0,
        "S22C2": 1.0,
        "S32C3": 0.0,
        "S42C4": 1.0,
        "S52C5": 1.0,
        "W_in2C1": 2.0
      },
      "vehicle_counts": {
        "C12C2": 23.0,
        "C12N1": 1.0,
        "C12S1": 2.0,
        "C12W_in": 6.0,
        "C22C1": 20.0,
        "C22C3": 23.0,
        "C22N2": 1.0,
        "C22S2": 1.0,
        "C32C2": 17.0,
        "C32C4": 17.0,
        "C32N3": 3.0,
        "C32S3": 3.0,
        "C42C3": 19.0,
        "C42C5": 22.0,
        "C42N4": 2.0,
        "C42S4": 1.0,
        "C52C4": 20.0,
        "C52E_out": 8.0,
        "C52N5": 2.0,
        "C52S5": 1.0,
        "E_out2C5": 7.0,
        "N12C1": 4.0,
        "N22C2": 4.0,
        "N32C3": 4.0,
        "N42C4": 4.0,
        "N52C5": 4.0,
        "S12C1": 4.0,
        "S22C2": 4.0,
        "S32C3": 4.0,
        "S42C4": 4.0,
        "S52C5": 4.0,
        "W_in2C1": 8.0
      },
      "capacities": {
        "C12C2": 109.12000000000002,
        "C12N1": 114.55999999999999,
        "C12S1": 114.55999999999999,
        "C12W_in": 114.55999999999999,
        "C22C1": 109.12000000000002,
        "C22C3": 109.12000000000002,
        "C22N2": 114.55999999999999,
        "C22S2": 114.55999999999999,
        "C32C2": 109.12000000000002,
        "C32C4": 109.12000000000002,
        "C32N3": 114.55999999999999,
        "C32S3": 114.55999999999999,
        "C42C3": 109.12000000000002,
        "C42C5": 109.12000000000002,
        "C42N4": 114.55999999999999,
        "C42S4": 114.55999999999999,
        "C52C4": 109.12000000000002,
        "C52E_out": 114.55999999999999,
        "C52N5": 114.55999999999999,
        "C52S5": 114.55999999999999,
        "E_out2C5": 114.55999999999999,
        "N12C1": 114.55999999999999,
        "N22C2": 114.55999999999999,
        "N32C3": 114.55999999999999,
        "N42C4": 114.55999999999999,
        "N52C5": 114.55999999999999,
        "S12C1": 114.55999999999999,
        "S22C2": 114.55999999999999,
        "S32C3": 114.55999999999999,
        "S42C4": 114.55999999999999,
        "S52C5": 114.55999999999999,
        "W_in2C1": 114.55999999999999
      },
      "tls_movements": {
        "C2": [
          [
            "C12C2",
            "C22C3"
          ],
          [
            "C12C2",
            "C22N2"
          ],
          [
            "C12C2",
            "C22S2"
          ],
          [
            "C32C2",
            "C22C1"
          ],
          [
            "C32C2",
            "C22N2"
          ],
          [
            "C32C2",
            "C22S2"
          ],
          [
            "N22C2",
            "C22C1"
          ],
          [
            "N22C2",
            "C22C3"
          ],
          [
            "N22C2",
            "C22S2"
          ],
          [
            "S22C2",
            "C22C1"
          ],
          [
            "S22C2",
            "C22C3"
          ],
          [
            "S22C2",
            "C22N2"
          ]
        ],
        "C1": [
          [
            "C22C1",
            "C12N1"
          ],
          [
            "C22C1",
            "C12S1"
          ],
          [
            "C22C1",
            "C12W_in"
          ],
          [
            "N12C1",
            "C12C2"
          ],
          [
            "N12C1",
            "C12S1"
          ],
          [
            "N12C1",
            "C12W_in"
          ],
          [
            "S12C1",
            "C12C2"
          ],
          [
            "S12C1",
            "C12N1"
          ],
          [
            "S12C1",
            "C12W_in"
          ],
          [
            "W_in2C1",
            "C12C2"
          ],
          [
            "W_in2C1",
            "C12N1"
          ],
          [
            "W_in2C1",
            "C12S1"
          ]
        ],
        "C3": [
          [
            "C22C3",
            "C32C4"
          ],
          [
            "C22C3",
            "C32N3"
          ],
          [
            "C22C3",
            "C32S3"
          ],
          [
            "C42C3",
            "C32C2"
          ],
          [
            "C42C3",
            "C32N3"
          ],
          [
            "C42C3",
            "C32S3"
          ],
          [
            "N32C3",
            "C32C2"
          ],
          [
            "N32C3",
            "C32C4"
          ],
          [
            "N32C3",
            "C32S3"
          ],
          [
            "S32C3",
            "C32C2"
          ],
          [
            "S32C3",
            "C32C4"
          ],
          [
            "S32C3",
            "C32N3"
          ]
        ],
        "C4": [
          [
            "C32C4",
            "C42C5"
          ],
          [
            "C32C4",
            "C42N4"
          ],
          [
            "C32C4",
            "C42S4"
          ],
          [
            "C52C4",
            "C42C3"
          ],
          [
            "C52C4",
            "C42N4"
          ],
          [
            "C52C4",
            "C42S4"
          ],
          [
            "N42C4",
            "C42C3"
          ],
          [
            "N42C4",
            "C42C5"
          ],
          [
            "N42C4",
            "C42S4"
          ],
          [
            "S42C4",
            "C42C3"
          ],
          [
            "S42C4",
            "C42C5"
          ],
          [
            "S42C4",
            "C42N4"
          ]
        ],
        "C5": [
          [
            "C42C5",
            "C52E_out"
          ],
          [
            "C42C5",
            "C52N5"
          ],
          [
            "C42C5",
            "C52S5"
          ],
          [
            "E_out2C5",
            "C52C4"
          ],
          [
            "E_out2C5",
            "C52N5"
          ],
          [
            "E_out2C5",
            "C52S5"
          ],
          [
            "N52C5",
            "C52C4"
          ],
          [
            "N52C5",
            "C52E_out"
          ],
          [
            "N52C5",
            "C52S5"
          ],
          [
            "S52C5",
            "C52C4"
          ],
          [
            "S52C5",
            "C52E_out"
          ],
          [
            "S52C5",
            "C52N5"
          ]
        ]
      }
    },
    {
      "time": 301.0,
      "queues": {
        "C12C2": 11.0,
        "C12N1": 0.0,
        "C12S1": 0.0,
        "C12W_in": 0.0,
        "C22C1": 12.0,
        "C22C3": 19.0,
        "C22N2": 0.0,
        "C22S2": 0.0,
        "C32C2": 12.0,
        "C32C4": 15.0,
        "C32N3": 0.0,
        "C32S3": 0.0,
        "C42C3": 10.0,
        "C42C5": 13.0,
        "C42N4": 0.0,
        "C42S4": 0.0,
        "C52C4": 16.0,
        "C52E_out": 0.0,
        "C52N5": 0.0,
        "C52S5": 0.0,
        "E_out2C5": 6.0,
        "N12C1": 0.0,
        "N22C2": 0.0,
        "N32C3": 0.0,
        "N42C4": 0.0,
        "N52C5": 0.0,
        "S12C1": 0.0,
        "S22C2": 0.0,
        "S32C3": 0.0,
        "S42C4": 0.0,
        "S52C5": 0.0,
        "W_in2C1": 9.0
      },
      "vehicle_counts": {
        "C12C2": 16.0,
        "C12N1": 1.0,
        "C12S1": 1.0,
        "C12W_in": 0.0,
        "C22C1": 19.0,
        "C22C3": 25.0,
        "C22N2": 1.0,
        "C22S2": 1.0,
        "C32C2": 18.0,
        "C32C4": 21.0,
        "C32N3": 0.0,
        "C32S3": 1.0,
        "C42C3": 15.0,
        "C42C5": 20.0,
        "C42N4": 1.0,
        "C42S4": 0.0,
        "C52C4": 22.0,
        "C52E_out": 1.0,
        "C52N5": 1.0,
        "C52S5": 1.0,
        "E_out2C5": 12.0,
        "N12C1": 4.0,
        "N22C2": 4.0,
        "N32C3": 2.0,
        "N42C4": 4.0,
        "N52C5": 2.0,
        "S12C1": 4.0,
        "S22C2": 2.0,
        "S32C3": 4.0,
        "S42C4": 4.0,
        "S52C5": 2.0,
        "W_in2C1": 14.0
      },
      "capacities": {
        "C12C2": 109.12000000000002,
        "C12N1": 114.55999999999999,
        "C12S1": 114.55999999999999,
        "C12W_in": 114.55999999999999,
        "C22C1": 109.12000000000002,
        "C22C3": 109.12000000000002,
        "C22N2": 114.55999999999999,
        "C22S2": 114.55999999999999,
        "C32C2": 109.12000000000002,
        "C32C4": 109.12000000000002,
        "C32N3": 114.55999999999999,
        "C32S3": 114.55999999999999,
        "C42C3": 109.12000000000002,
        "C42C5": 109.12000000000002,
        "C42N4": 114.55999999999999,
        "C42S4": 114.55999999999999,
        "C52C4": 109.12000000000002,
        "C52E_out": 114.55999999999999,
        "C52N5": 114.55999999999999,
        "C52S5": 114.55999999999999,
        "E_out2C5": 114.55999999999999,
        "N12C1": 114.55999999999999,
        "N22C2": 114.55999999999999,
        "N32C3": 114.55999999999999,
        "N42C4": 114.55999999999999,
        "N52C5": 114.55999999999999,
        "S12C1": 114.55999999999999,
        "S22C2": 114.55999999999999,
        "S32C3": 114.55999999999999,
        "S42C4": 114.55999999999999,
        "S52C5": 114.55999999999999,
        "W_in2C1": 114.55999999999999
      },
      "tls_movements": {
        "C2": [
          [
            "C12C2",
            "C22C3"
          ],
          [
            "C12C2",
            "C22N2"
          ],
          [
            "C12C2",
            "C22S2"
          ],
          [
            "C32C2",
            "C22C1"
          ],
          [
            "C32C2",
            "C22N2"
          ],
          [
            "C32C2",
            "C22S2"
          ],
          [
            "N22C2",
            "C22C1"
          ],
          [
            "N22C2",
            "C22C3"
          ],
          [
            "N22C2",
            "C22S2"
          ],
          [
            "S22C2",
            "C22C1"
          ],
          [
            "S22C2",
            "C22C3"
          ],
          [
            "S22C2",
            "C22N2"
          ]
        ],
        "C1": [
          [
            "C22C1",
            "C12N1"
          ],
          [
            "C22C1",
            "C12S1"
          ],
          [
            "C22C1",
            "C12W_in"
          ],
          [
            "N12C1",
            "C12C2"
          ],
          [
            "N12C1",
            "C12S1"
          ],
          [
            "N12C1",
            "C12W_in"
          ],
          [
            "S12C1",
            "C12C2"
          ],
          [
            "S12C1",
            "C12N1"
          ],
          [
            "S12C1",
            "C12W_in"
          ],
          [
            "W_in2C1",
            "C12C2"
          ],
          [
            "W_in2C1",
            "C12N1"
          ],
          [
            "W_in2C1",
            "C12S1"
          ]
        ],
        "C3": [
          [
            "C22C3",
            "C32C4"
          ],
          [
            "C22C3",
            "C32N3"
          ],
          [
            "C22C3",
            "C32S3"
          ],
          [
            "C42C3",
            "C32C2"
          ],
          [
            "C42C3",
            "C32N3"
          ],
          [
            "C42C3",
            "C32S3"
          ],
          [
            "N32C3",
            "C32C2"
          ],
          [
            "N32C3",
            "C32C4"
          ],
          [
            "N32C3",
            "C32S3"
          ],
          [
            "S32C3",
            "C32C2"
          ],
          [
            "S32C3",
            "C32C4"
          ],
          [
            "S32C3",
            "C32N3"
          ]
        ],
        "C4": [
          [
            "C32C4",
            "C42C5"
          ],
          [
            "C32C4",
            "C42N4"
          ],
          [
            "C32C4",
            "C42S4"
          ],
          [
            "C52C4",
            "C42C3"
          ],
          [
            "C52C4",
            "C42N4"
          ],
          [
            "C52C4",
            "C42S4"
          ],
          [
            "N42C4",
            "C42C3"
          ],
          [
            "N42C4",
            "C42C5"
          ],
          [
            "N42C4",
            "C42S4"
          ],
          [
            "S42C4",
            "C42C3"
          ],
          [
            "S42C4",
            "C42C5"
          ],
          [
            "S42C4",
            "C42N4"
          ]
        ],
        "C5": [
          [
            "C42C5",
            "C52E_out"
          ],
          [
            "C42C5",
            "C52N5"
          ],
          [
            "C42C5",
            "C52S5"
          ],
          [
            "E_out2C5",
            "C52C4"
          ],
          [
            "E_out2C5",
            "C52N5"
          ],
          [
            "E_out2C5",
            "C52S5"
          ],
          [
            "N52C5",
            "C52C4"
          ],
          [
            "N52C5",
            "C52E_out"
          ],
          [
            "N52C5",
            "C52S5"
          ],
          [
            "S52C5",
            "C52C4"
          ],
          [
            "S52C5",
            "C52E_out"
          ],
          [
            "S52C5",
            "C52N5"
          ]
        ]
      }
    },
    {
      "time": 361.0,
      "queues": {
        "C12C2": 1.0,
        "C12N1": 0.0,
        "C12S1": 0.0,
        "C12W_in": 0.0,
        "C22C1": 1.0,
        "C22C3": 3.0,
        "C22N2": 0.0,
        "C22S2": 0.0,
        "C32C2": 0.0,
        "C32C4": 1.0,
        "C32N3": 0.0,
        "C32S3": 0.0,
        "C42C3": 1.0,
        "C42C5": 0.0,
        "C42N4": 0.0,
        "C42S4": 0.0,
        "C52C4": 0.0,
        "C52E_out": 0.0,
        "C52N5": 0.0,
        "C52S5": 0.0,
        "E_out2C5": 0.0,
        "N12C1": 1.0,
        "N22C2": 1.0,
        "N32C3": 1.0,
        "N42C4": 1.0,
        "N52C5": 1.0,
        "S12C1": 1.0,
        "S22C2": 1.0,
        "S32C3": 1.0,
        "S42C4": 1.0,
        "S52C5": 1.0,
        "W_in2C1": 0.0
      },
      "vehicle_counts": {
        "C12C2": 13.0,
        "C12N1": 4.0,
        "C12S1": 3.0,
        "C12W_in": 2.0,
        "C22C1": 12.0,
        "C22C3": 16.0,
        "C22N2": 3.0,
        "C22S2": 4.0,
        "C32C2": 9.0,
        "C32C4": 12.0,
        "C32N3": 3.0,
        "C32S3": 5.0,
        "C42C3": 12.0,
        "C42C5": 11.0,
        "C42N4": 2.0,
        "C42S4": 5.0,
        "C52C4": 11.0,
        "C52E_out": 4.0,
        "C52N5": 4.0,
        "C52S5": 4.0,
        "E_out2C5": 6.0,
        "N12C1": 5.0,
        "N22C2": 5.0,
        "N32C3": 5.0,
        "N42C4": 4.0,
        "N52C5": 5.0,
        "S12C1": 4.0,
        "S22C2": 5.0,
        "S32C3": 5.0,
        "S42C4": 5.0,
        "S52C5": 5.0,
        "W_in2C1": 6.0
      },
      "capacities": {
        "C12C2": 109.12000000000002,
        "C12N1": 114.55999999999999,
        "C12S1": 114.55999999999999,
        "C12W_in": 114.55999999999999,
        "C22C1": 109.12000000000002,
        "C22C3": 109.12000000000002,
        "C22N2": 114.55999999999999,
        "C22S2": 114.55999999999999,
        "C32C2": 109.12000000000002,
        "C32C4": 109.12000000000002,
        "C32N3": 114.55999999999999,
        "C32S3": 114.55999999999999,
        "C42C3": 109.12000000000002,
        "C42C5": 109.12000000000002,
        "C42N4": 114.55999999999999,
        "C42S4": 114.55999999999999,
        "C52C4": 109.12000000000002,
        "C52E_out": 114.55999999999999,
        "C52N5": 114.55999999999999,
        "C52S5": 114.55999999999999,
        "E_out2C5": 114.55999999999999,
        "N12C1": 114.55999999999999,
        "N22C2": 114.55999999999999,
        "N32C3": 114.55999999999999,
        "N42C4": 114.55999999999999,
        "N52C5": 114.55999999999999,
        "S12C1": 114.55999999999999,
        "S22C2": 114.55999999999999,
        "S32C3": 114.55999999999999,
        "S42C4": 114.55999999999999,
        "S52C5": 114.55999999999999,
        "W_in2C1": 114.55999999999999
      },
      "tls_movements": {
        "C2": [
          [
            "C12C2",
            "C22C3"
          ],
          [
            "C12C2",
            "C22N2"
          ],
          [
            "C12C2",
            "C22S2"
          ],
          [
            "C32C2",
            "C22C1"
          ],
          [
            "C32C2",
            "C22N2"
          ],
          [
            "C32C2",
            "C22S2"
          ],
          [
            "N22C2",
            "C22C1"
          ],
          [
            "N22C2",
            "C22C3"
          ],
          [
            "N22C2",
            "C22S2"
          ],
          [
            "S22C2",
            "C22C1"
          ],
          [
            "S22C2",
            "C22C3"
          ],
          [
            "S22C2",
            "C22N2"
          ]
        ],
        "C1": [
          [
            "C22C1",
            "C12N1"
          ],
          [
            "C22C1",
            "C12S1"
          ],
          [
            "C22C1",
            "C12W_in"
          ],
          [
            "N12C1",
            "C12C2"
          ],
          [
            "N12C1",
            "C12S1"
          ],
          [
            "N12C1",
            "C12W_in"
          ],
          [
            "S12C1",
            "C12C2"
          ],
          [
            "S12C1",
            "C12N1"
          ],
          [
            "S12C1",
            "C12W_in"
          ],
          [
            "W_in2C1",
            "C12C2"
          ],
          [
            "W_in2C1",
            "C12N1"
          ],
          [
            "W_in2C1",
            "C12S1"
          ]
        ],
        "C3": [
          [
            "C22C3",
            "C32C4"
          ],
          [
            "C22C3",
            "C32N3"
          ],
          [
            "C22C3",
            "C32S3"
          ],
          [
            "C42C3",
            "C32C2"
          ],
          [
            "C42C3",
            "C32N3"
          ],
          [
            "C42C3",
            "C32S3"
          ],
          [
            "N32C3",
            "C32C2"
          ],
          [
            "N32C3",
            "C32C4"
          ],
          [
            "N32C3",
            "C32S3"
          ],
          [
            "S32C3",
            "C32C2"
          ],
          [
            "S32C3",
            "C32C4"
          ],
          [
            "S32C3",
            "C32N3"
          ]
        ],
        "C4": [
          [
            "C32C4",
            "C42C5"
          ],
          [
            "C32C4",
            "C42N4"
          ],
          [
            "C32C4",
            "C42S4"
          ],
          [
            "C52C4",
            "C42C3"
          ],
          [
            "C52C4",
            "C42N4"
          ],
          [
            "C52C4",
            "C42S4"
          ],
          [
            "N42C4",
            "C42C3"
          ],
          [
            "N42C4",
            "C42C5"
          ],
          [
            "N42C4",
            "C42S4"
          ],
          [
            "S42C4",
            "C42C3"
          ],
          [
            "S42C4",
            "C42C5"
          ],
          [
            "S42C4",
            "C42N4"
          ]
        ],
        "C5": [
          [
            "C42C5",
            "C52E_out"
          ],
          [
            "C42C5",
            "C52N5"
          ],
          [
            "C42C5",
            "C52S5"
          ],
          [
            "E_out2C5",
            "C52C4"
          ],
          [
            "E_out2C5",
            "C52N5"
          ],
          [
            "E_out2C5",
            "C52S5"
          ],
          [
            "N52C5",
            "C52C4"
          ],
          [
            "N52C5",
            "C52E_out"
          ],
          [
            "N52C5",
            "C52S5"
          ],
          [
            "S52C5",
            "C52C4"
          ],
          [
            "S52C5",
            "C52E_out"
          ],
          [
            "S52C5",
            "C52N5"
          ]
        ]
      }
    },
    {
      "time": 421.0,
      "queues": {
        "C12C2": 3.0,
        "C12N1": 0.0,
        "C12S1": 0.0,
        "C12W_in": 0.0,
        "C22C1": 7.0,
        "C22C3": 7.0,
        "C22N2": 0.0,
        "C22S2": 0.0,
        "C32C2": 0.0,
        "C32C4": 3.0,
        "C32N3": 0.0,
        "C32S3": 0.0,
        "C42C3": 1.0,
        "C42C5": 0.0,
        "C42N4": 0.0,
        "C42S4": 0.0,
        "C52C4": 6.0,
        "C52E_out": 0.0,
        "C52N5": 0.0,
        "C52S5": 0.0,
        "E_out2C5": 0.0,
        "N12C1": 1.0,
        "N22C2": 0.0,
        "N32C3": 1.0,
        "N42C4": 0.0,
        "N52C5": 0.0,
        "S12C1": 1.0,
        "S22C2": 0.0,
        "S32C3": 0.0,
        "S42C4": 0.0,
        "S52C5": 0.0,
        "W_in2C1": 1.0
      },
      "vehicle_counts": {
        "C12C2": 23.0,
        "C12N1": 1.0,
        "C12S1": 2.0,
        "C12W_in": 8.0,
        "C22C1": 23.0,
        "C22C3": 23.0,
        "C22N2": 3.0,
        "C22S2": 3.0,
        "C32C2": 13.0,
        "C32C4": 21.0,
        "C32N3": 2.0,
        "C32S3": 1.0,
        "C42C3": 16.0,
        "C42C5": 20.0,
        "C42N4": 1.0,
        "C42S4": 3.0,
        "C52C4": 21.0,
        "C52E_out": 8.0,
        "C52N5": 3.0,
        "C52S5": 3.0,
        "E_out2C5": 7.0,
        "N12C1": 4.0,
        "N22C2": 4.0,
        "N32C3": 5.0,
        "N42C4": 4.0,
        "N52C5": 4.0,
        "S12C1": 4.0,
        "S22C2": 4.0,
        "S32C3": 4.0,
        "S42C4": 4.0,
        "S52C5": 4.0,
        "W_in2C1": 8.0
      },
      "capacities": {
        "C12C2": 109.12000000000002,
        "C12N1": 114.55999999999999,
        "C12S1": 114.55999999999999,
        "C12W_in": 114.55999999999999,
        "C22C1": 109.12000000000002,
        "C22C3": 109.12000000000002,
        "C22N2": 114.55999999999999,
        "C22S2": 114.55999999999999,
        "C32C2": 109.12000000000002,
        "C32C4": 109.12000000000002,
        "C32N3": 114.55999999999999,
        "C32S3": 114.55999999999999,
        "C42C3": 109.12000000000002,
        "C42C5": 109.12000000000002,
        "C42N4": 114.55999999999999,
        "C42S4": 114.55999999999999,
        "C52C4": 109.12000000000002,
        "C52E_out": 114.55999999999999,
        "C52N5": 114.55999999999999,
        "C52S5": 114.55999999999999,
        "E_out2C5": 114.55999999999999,
        "N12C1": 114.55999999999999,
        "N22C2": 114.55999999999999,
        "N32C3": 114.55999999999999,
        "N42C4": 114.55999999999999,
        "N52C5": 114.55999999999999,
        "S12C1": 114.55999999999999,
        "S22C2": 114.55999999999999,
        "S32C3": 114.55999999999999,
        "S42C4": 114.55999999999999,
        "S52C5": 114.55999999999999,
        "W_in2C1": 114.55999999999999
      },
      "tls_movements": {
        "C2": [
          [
            "C12C2",
            "C22C3"
          ],
          [
            "C12C2",
            "C22N2"
          ],
          [
            "C12C2",
            "C22S2"
          ],
          [
            "C32C2",
            "C22C1"
          ],
          [
            "C32C2",
            "C22N2"
          ],
          [
            "C32C2",
            "C22S2"
          ],
          [
            "N22C2",
            "C22C1"
          ],
          [
            "N22C2",
            "C22C3"
          ],
          [
            "N22C2",
            "C22S2"
          ],
          [
            "S22C2",
            "C22C1"
          ],
          [
            "S22C2",
            "C22C3"
          ],
          [
            "S22C2",
            "C22N2"
          ]
        ],
        "C1": [
          [
            "C22C1",
            "C12N1"
          ],
          [
            "C22C1",
            "C12S1"
          ],
          [
            "C22C1",
            "C12W_in"
          ],
          [
            "N12C1",
            "C12C2"
          ],
          [
            "N12C1",
            "C12S1"
          ],
          [
            "N12C1",
            "C12W_in"
          ],
          [
            "S12C1",
            "C12C2"
          ],
          [
            "S12C1",
            "C12N1"
          ],
          [
            "S12C1",
            "C12W_in"
          ],
          [
            "W_in2C1",
            "C12C2"
          ],
          [
            "W_in2C1",
            "C12N1"
          ],
          [
            "W_in2C1",
            "C12S1"
          ]
        ],
        "C3": [
          [
            "C22C3",
            "C32C4"
          ],
          [
            "C22C3",
            "C32N3"
          ],
          [
            "C22C3",
            "C32S3"
          ],
          [
            "C42C3",
            "C32C2"
          ],
          [
            "C42C3",
            "C32N3"
          ],
          [
            "C42C3",
            "C32S3"
          ],
          [
            "N32C3",
            "C32C2"
          ],
          [
            "N32C3",
            "C32C4"
          ],
          [
            "N32C3",
            "C32S3"
          ],
          [
            "S32C3",
            "C32C2"
          ],
          [
            "S32C3",
            "C32C4"
          ],
          [
            "S32C3",
            "C32N3"
          ]
        ],
        "C4": [
          [
            "C32C4",
            "C42C5"
          ],
          [
            "C32C4",
            "C42N4"
          ],
          [
            "C32C4",
            "C42S4"
          ],
          [
            "C52C4",
            "C42C3"
          ],
          [
            "C52C4",
            "C42N4"
          ],
          [
            "C52C4",
            "C42S4"
          ],
          [
            "N42C4",
            "C42C3"
          ],
          [
            "N42C4",
            "C42C5"
          ],
          [
            "N42C4",
            "C42S4"
          ],
          [
            "S42C4",
            "C42C3"
          ],
          [
            "S42C4",
            "C42C5"
          ],
          [
            "S42C4",
            "C42N4"
          ]
        ],
        "C5": [
          [
            "C42C5",
            "C52E_out"
          ],
          [
            "C42C5",
            "C52N5"
          ],
          [
            "C42C5",
            "C52S5"
          ],
          [
            "E_out2C5",
            "C52C4"
          ],
          [
            "E_out2C5",
            "C52N5"
          ],
          [
            "E_out2C5",
            "C52S5"
          ],
          [
            "N52C5",
            "C52C4"
          ],
          [
            "N52C5",
            "C52E_out"
          ],
          [
            "N52C5",
            "C52S5"
          ],
          [
            "S52C5",
            "C52C4"
          ],
          [
            "S52C5",
            "C52E_out"
          ],
          [
            "S52C5",
            "C52N5"
          ]
        ]
      }
    },
    {
      "time": 481.0,
      "queues": {
        "C12C2": 13.0,
        "C12N1": 0.0,
        "C12S1": 0.0,
        "C12W_in": 0.0,
        "C22C1": 13.0,
        "C22C3": 17.0,
        "C22N2": 0.0,
        "C22S2": 0.0,
        "C32C2": 8.0,
        "C32C4": 18.0,
        "C32N3": 0.0,
        "C32S3": 0.0,
        "C42C3": 12.0,
        "C42C5": 11.0,
        "C42N4": 0.0,
        "C42S4": 0.0,
        "C52C4": 13.0,
        "C52E_out": 0.0,
        "C52N5": 0.0,
        "C52S5": 0.0,
        "E_out2C5": 7.0,
        "N12C1": 0.0,
        "N22C2": 0.0,
        "N32C3": 0.0,
        "N42C4": 0.0,
        "N52C5": 0.0,
        "S12C1": 0.0,
        "S22C2": 0.0,
        "S32C3": 0.0,
        "S42C4": 0.0,
        "S52C5": 0.0,
        "W_in2C1": 10.0
      },
      "vehicle_counts": {
        "C12C2": 19.0,
        "C12N1": 1.0,
        "C12S1": 0.0,
        "C12W_in": 1.0,
        "C22C1": 19.0,
        "C22C3": 23.0,
        "C22N2": 1.0,
        "C22S2": 1.0,
        "C32C2": 15.0,
        "C32C4": 24.0,
        "C32N3": 1.0,
        "C32S3": 2.0,
        "C42C3": 19.0,
        "C42C5": 16.0,
        "C42N4": 1.0,
        "C42S4": 2.0,
        "C52C4": 20.0,
        "C52E_out": 1.0,
        "C52N5": 1.0,
        "C52S5": 1.0,
        "E_out2C5": 13.0,
        "N12C1": 2.0,
        "N22C2": 4.0,
        "N32C3": 4.0,
        "N42C4": 4.0,
        "N52C5": 4.0,
        "S12C1": 4.0,
        "S22C2": 4.0,
        "S32C3": 2.0,
        "S42C4": 4.0,
        "S52C5": 2.0,
        "W_in2C1": 15.0
      },
      "capacities": {
        "C12C2": 109.12000000000002,
        "C12N1": 114.55999999999999,
        "C12S1": 114.55999999999999,
        "C12W_in": 114.55999999999999,
        "C22C1": 109.12000000000002,
        "C22C3": 109.12000000000002,
        "C22N2": 114.55999999999999,
        "C22S2": 114.55999999999999,
        "C32C2": 109.12000000000002,
        "C32C4": 109.12000000000002,
        "C32N3": 114.55999999999999,
        "C32S3": 114.55999999999999,
        "C42C3": 109.12000000000002,
        "C42C5": 109.12000000000002,
        "C42N4": 114.55999999999999,
        "C42S4": 114.55999999999999,
        "C52C4": 109.12000000000002,
        "C52E_out": 114.55999999999999,
        "C52N5": 114.55999999999999,
        "C52S5": 114.55999999999999,
        "E_out2C5": 114.55999999999999,
        "N12C1": 114.55999999999999,
        "N22C2": 114.55999999999999,
        "N32C3": 114.55999999999999,
        "N42C4": 114.55999999999999,
        "N52C5": 114.55999999999999,
        "S12C1": 114.55999999999999,
        "S22C2": 114.55999999999999,
        "S32C3": 114.55999999999999,
        "S42C4": 114.55999999999999,
        "S52C5": 114.55999999999999,
        "W_in2C1": 114.55999999999999
      },
      "tls_movements": {
        "C2": [
          [
            "C12C2",
            "C22C3"
          ],
          [
            "C12C2",
            "C22N2"
          ],
          [
            "C12C2",
            "C22S2"
          ],
          [
            "C32C2",
            "C22C1"
          ],
          [
            "C32C2",
            "C22N2"
          ],
          [
            "C32C2",
            "C22S2"
          ],
          [
            "N22C2",
            "C22C1"
          ],
          [
            "N22C2",
            "C22C3"
          ],
          [
            "N22C2",
            "C22S2"
          ],
          [
            "S22C2",
            "C22C1"
          ],
          [
            "S22C2",
            "C22C3"
          ],
          [
            "S22C2",
            "C22N2"
          ]
        ],
        "C1": [
          [
            "C22C1",
            "C12N1"
          ],
          [
            "C22C1",
            "C12S1"
          ],
          [
            "C22C1",
            "C12W_in"
          ],
          [
            "N12C1",
            "C12C2"
          ],
          [
            "N12C1",
            "C12S1"
          ],
          [
            "N12C1",
            "C12W_in"
          ],
          [
            "S12C1",
            "C12C2"
          ],
          [
            "S12C1",
            "C12N1"
          ],
          [
            "S12C1",
            "C12W_in"
          ],
          [
            "W_in2C1",
            "C12C2"
          ],
          [
            "W_in2C1",
            "C12N1"
          ],
          [
            "W_in2C1",
            "C12S1"
          ]
        ],
        "C3": [
          [
            "C22C3",
            "C32C4"
          ],
          [
            "C22C3",
            "C32N3"
          ],
          [
            "C22C3",
            "C32S3"
          ],
          [
            "C42C3",
            "C32C2"
          ],
          [
            "C42C3",
            "C32N3"
          ],
          [
            "C42C3",
            "C32S3"
          ],
          [
            "N32C3",
            "C32C2"
          ],
          [
            "N32C3",
            "C32C4"
          ],
          [
            "N32C3",
            "C32S3"
          ],
          [
            "S32C3",
            "C32C2"
          ],
          [
            "S32C3",
            "C32C4"
          ],
          [
            "S32C3",
            "C32N3"
          ]
        ],
        "C4": [
          [
            "C32C4",
            "C42C5"
          ],
          [
            "C32C4",
            "C42N4"
          ],
          [
            "C32C4",
            "C42S4"
          ],
          [
            "C52C4",
            "C42C3"
          ],
          [
            "C52C4",
            "C42N4"
          ],
          [
            "C52C4",
            "C42S4"
          ],
          [
            "N42C4",
            "C42C3"
          ],
          [
            "N42C4",
            "C42C5"
          ],
          [
            "N42C4",
            "C42S4"
          ],
          [
            "S42C4",
            "C42C3"
          ],
          [
            "S42C4",
            "C42C5"
          ],
          [
            "S42C4",
            "C42N4"
          ]
        ],
        "C5": [
          [
            "C42C5",
            "C52E_out"
          ],
          [
            "C42C5",
            "C52N5"
          ],
          [
            "C42C5",
            "C52S5"
          ],
          [
            "E_out2C5",
            "C52C4"
          ],
          [
            "E_out2C5",
            "C52N5"
          ],
          [
            "E_out2C5",
            "C52S5"
          ],
          [
            "N52C5",
            "C52C4"
          ],
          [
            "N52C5",
            "C52E_out"
          ],
          [
            "N52C5",
            "C52S5"
          ],
          [
            "S52C5",
            "C52C4"
          ],
          [
            "S52C5",
            "C52E_out"
          ],
          [
            "S52C5",
            "C52N5"
          ]
        ]
      }
    },
    {
      "time": 541.0,
      "queues": {
        "C12C2": 1.0,
        "C12N1": 0.0,
        "C12S1": 0.0,
        "C12W_in": 0.0,
        "C22C1": 3.0,
        "C22C3": 1.0,
        "C22N2": 0.0,
        "C22S2": 0.0,
        "C32C2": 0.0,
        "C32C4": 0.0,
        "C32N3": 0.0,
        "C32S3": 0.0,
        "C42C3": 0.0,
        "C42C5": 0.0,
        "C42N4": 0.0,
        "C42S4": 0.0,
        "C52C4": 0.0,
        "C52E_out": 0.0,
        "C52N5": 0.0,
        "C52S5": 0.0,
        "E_out2C5": 0.0,
        "N12C1": 1.0,
        "N22C2": 1.0,
        "N32C3": 1.0,
        "N42C4": 1.0,
        "N52C5": 1.0,
        "S12C1": 1.0,
        "S22C2": 1.0,
        "S32C3": 1.0,
        "S42C4": 1.0,
        "S52C5": 1.0,
        "W_in2C1": 0.0
      },
      "vehicle_counts": {
        "C12C2": 12.0,
        "C12N1": 2.0,
        "C12S1": 3.0,
        "C12W_in": 3.0,
        "C22C1": 11.0,
        "C22C3": 16.0,
        "C22N2": 3.0,
        "C22S2": 2.0,
        "C32C2": 9.0,
        "C32C4": 14.0,
        "C32N3": 5.0,
        "C32S3": 3.0,
        "C42C3": 14.0,
        "C42C5": 10.0,
        "C42N4": 2.0,
        "C42S4": 4.0,
        "C52C4": 9.0,
        "C52E_out": 3.0,
        "C52N5": 3.0,
        "C52S5": 4.0,
        "E_out2C5": 6.0,
        "N12C1": 5.0,
        "N22C2": 4.0,
        "N32C3": 4.0,
        "N42C4": 5.0,
        "N52C5": 4.0,
        "S12C1": 6.0,
        "S22C2": 6.0,
        "S32C3": 5.0,
        "S42C4": 6.0,
        "S52C5": 5.0,
        "W_in2C1": 7.0
      },
      "capacities": {
        "C12C2": 109.12000000000002,
        "C12N1": 114.55999999999999,
        "C12S1": 114.55999999999999,
        "C12W_in": 114.55999999999999,
        "C22C1": 109.12000000000002,
        "C22C3": 109.12000000000002,
        "C22N2": 114.55999999999999,
        "C22S2": 114.55999999999999,
        "C32C2": 109.12000000000002,
        "C32C4": 109.12000000000002,
        "C32N3": 114.55999999999999,
        "C32S3": 114.55999999999999,
        "C42C3": 109.12000000000002,
        "C42C5": 109.12000000000002,
        "C42N4": 114.55999999999999,
        "C42S4": 114.55999999999999,
        "C52C4": 109.12000000000002,
        "C52E_out": 114.55999999999999,
        "C52N5": 114.55999999999999,
        "C52S5": 114.55999999999999,
        "E_out2C5": 114.55999999999999,
        "N12C1": 114.55999999999999,
        "N22C2": 114.55999999999999,
        "N32C3": 114.55999999999999,
        "N42C4": 114.55999999999999,
        "N52C5": 114.55999999999999,
        "S12C1": 114.55999999999999,
        "S22C2": 114.55999999999999,
        "S32C3": 114.55999999999999,
        "S42C4": 114.55999999999999,
        "S52C5": 114.55999999999999,
        "W_in2C1": 114.55999999999999
      },
      "tls_movements": {
        "C2": [
          [
            "C12C2",
            "C22C3"
          ],
          [
            "C12C2",
            "C22N2"
          ],
          [
            "C12C2",
            "C22S2"
          ],
          [
            "C32C2",
            "C22C1"
          ],
          [
            "C32C2",
            "C22N2"
          ],
          [
            "C32C2",
            "C22S2"
          ],
          [
            "N22C2",
            "C22C1"
          ],
          [
            "N22C2",
            "C22C3"
          ],
          [
            "N22C2",
            "C22S2"
          ],
          [
            "S22C2",
            "C22C1"
          ],
          [
            "S22C2",
            "C22C3"
          ],
          [
            "S22C2",
            "C22N2"
          ]
        ],
        "C1": [
          [
            "C22C1",
            "C12N1"
          ],
          [
            "C22C1",
            "C12S1"
          ],
          [
            "C22C1",
            "C12W_in"
          ],
          [
            "N12C1",
            "C12C2"
          ],
          [
            "N12C1",
            "C12S1"
          ],
          [
            "N12C1",
            "C12W_in"
          ],
          [
            "S12C1",
            "C12C2"
          ],
          [
            "S12C1",
            "C12N1"
          ],
          [
            "S12C1",
            "C12W_in"
          ],
          [
            "W_in2C1",
            "C12C2"
          ],
          [
            "W_in2C1",
            "C12N1"
          ],
          [
            "W_in2C1",
            "C12S1"
          ]
        ],
        "C3": [
          [
            "C22C3",
            "C32C4"
          ],
          [
            "C22C3",
            "C32N3"
          ],
          [
            "C22C3",
            "C32S3"
          ],
          [
            "C42C3",
            "C32C2"
          ],
          [
            "C42C3",
            "C32N3"
          ],
          [
            "C42C3",
            "C32S3"
          ],
          [
            "N32C3",
            "C32C2"
          ],
          [
            "N32C3",
            "C32C4"
          ],
          [
            "N32C3",
            "C32S3"
          ],
          [
            "S32C3",
            "C32C2"
          ],
          [
            "S32C3",
            "C32C4"
          ],
          [
            "S32C3",
            "C32N3"
          ]
        ],
        "C4": [
          [
            "C32C4",
            "C42C5"
          ],
          [
            "C32C4",
            "C42N4"
          ],
          [
            "C32C4",
            "C42S4"
          ],
          [
            "C52C4",
            "C42C3"
          ],
          [
            "C52C4",
            "C42N4"
          ],
          [
            "C52C4",
            "C42S4"
          ],
          [
            "N42C4",
            "C42C3"
          ],
          [
            "N42C4",
            "C42C5"
          ],
          [
            "N42C4",
            "C42S4"
          ],
          [
            "S42C4",
            "C42C3"
          ],
          [
            "S42C4",
            "C42C5"
          ],
          [
            "S42C4",
            "C42N4"
          ]
        ],
        "C5": [
          [
            "C42C5",
            "C52E_out"
          ],
          [
            "C42C5",
            "C52N5"
          ],
          [
            "C42C5",
            "C52S5"
          ],
          [
            "E_out2C5",
            "C52C4"
          ],
          [
            "E_out2C5",
            "C52N5"
          ],
          [
            "E_out2C5",
            "C52S5"
          ],
          [
            "N52C5",
            "C52C4"
          ],
          [
            "N52C5",
            "C52E_out"
          ],
          [
            "N52C5",
            "C52S5"
          ],
          [
            "S52C5",
            "C52C4"
          ],
          [
            "S52C5",
            "C52E_out"
          ],
          [
            "S52C5",
            "C52N5"
          ]
        ]
      }
    },
    {
      "time": 601.0,
      "queues": {
        "C12C2": 6.0,
        "C12N1": 0.0,
        "C12S1": 0.0,
        "C12W_in": 0.0,
        "C22C1": 7.0,
        "C22C3": 6.0,
        "C22N2": 0.0,
        "C22S2": 0.0,
        "C32C2": 0.0,
        "C32C4": 7.0,
        "C32N3": 0.0,
        "C32S3": 0.0,
        "C42C3": 2.0,
        "C42C5": 0.0,
        "C42N4": 0.0,
        "C42S4": 0.0,
        "C52C4": 1.0,
        "C52E_out": 0.0,
        "C52N5": 0.0,
        "C52S5": 0.0,
        "E_out2C5": 1.0,
        "N12C1": 1.0,
        "N22C2": 0.0,
        "N32C3": 1.0,
        "N42C4": 0.0,
        "N52C5": 1.0,
        "S12C1": 0.0,
        "S22C2": 1.0,
        "S32C3": 0.0,
        "S42C4": 1.0,
        "S52C5": 0.0,
        "W_in2C1": 2.0
      },
      "vehicle_counts": {
        "C12C2": 21.0,
        "C12N1": 1.0,
        "C12S1": 2.0,
        "C12W_in": 7.0,
        "C22C1": 20.0,
        "C22C3": 25.0,
        "C22N2": 2.0,
        "C22S2": 3.0,
        "C32C2": 15.0,
        "C32C4": 21.0,
        "C32N3": 1.0,
        "C32S3": 1.0,
        "C42C3": 24.0,
        "C42C5": 16.0,
        "C42N4": 2.0,
        "C42S4": 2.0,
        "C52C4": 16.0,
        "C52E_out": 6.0,
        "C52N5": 3.0,
        "C52S5": 2.0,
        "E_out2C5": 8.0,
        "N12C1": 4.0,
        "N22C2": 4.0,
        "N32C3": 4.0,
        "N42C4": 4.0,
        "N52C5": 4.0,
        "S12C1": 4.0,
        "S22C2": 4.0,
        "S32C3": 4.0,
        "S42C4": 5.0,
        "S52C5": 4.0,
        "W_in2C1": 9.0
      },
      "capacities": {
        "C12C2": 109.12000000000002,
        "C12N1": 114.55999999999999,
        "C12S1": 114.55999999999999,
        "C12W_in": 114.55999999999999,
        "C22C1": 109.12000000000002,
        "C22C3": 109.12000000000002,
        "C22N2": 114.55999999999999,
        "C22S2": 114.55999999999999,
        "C32C2": 109.12000000000002,
        "C32C4": 109.12000000000002,
        "C32N3": 114.55999999999999,
        "C32S3": 114.55999999999999,
        "C42C3": 109.12000000000002,
        "C42C5": 109.12000000000002,
        "C42N4": 114.55999999999999,
        "C42S4": 114.55999999999999,
        "C52C4": 109.12000000000002,
        "C52E_out": 114.55999999999999,
        "C52N5": 114.55999999999999,
        "C52S5": 114.55999999999999,
        "E_out2C5": 114.55999999999999,
        "N12C1": 114.55999999999999,
        "N22C2": 114.55999999999999,
        "N32C3": 114.55999999999999,
        "N42C4": 114.55999999999999,
        "N52C5": 114.55999999999999,
        "S12C1": 114.55999999999999,
        "S22C2": 114.55999999999999,
        "S32C3": 114.55999999999999,
        "S42C4": 114.55999999999999,
        "S52C5": 114.55999999999999,
        "W_in2C1": 114.55999999999999
      },
      "tls_movements": {
        "C2": [
          [
            "C12C2",
            "C22C3"
          ],
          [
            "C12C2",
            "C22N2"
          ],
          [
            "C12C2",
            "C22S2"
          ],
          [
            "C32C2",
            "C22C1"
          ],
          [
            "C32C2",
            "C22N2"
          ],
          [
            "C32C2",
            "C22S2"
          ],
          [
            "N22C2",
            "C22C1"
          ],
          [
            "N22C2",
            "C22C3"
          ],
          [
            "N22C2",
            "C22S2"
          ],
          [
            "S22C2",
            "C22C1"
          ],
          [
            "S22C2",
            "C22C3"
          ],
          [
            "S22C2",
            "C22N2"
          ]
        ],
        "C1": [
          [
            "C22C1",
            "C12N1"
          ],
          [
            "C22C1",
            "C12S1"
          ],
          [
            "C22C1",
            "C12W_in"
          ],
          [
            "N12C1",
            "C12C2"
          ],
          [
            "N12C1",
            "C12S1"
          ],
          [
            "N12C1",
            "C12W_in"
          ],
          [
            "S12C1",
            "C12C2"
          ],
          [
            "S12C1",
            "C12N1"
          ],
          [
            "S12C1",
            "C12W_in"
          ],
          [
            "W_in2C1",
            "C12C2"
          ],
          [
            "W_in2C1",
            "C12N1"
          ],
          [
            "W_in2C1",
            "C12S1"
          ]
        ],
        "C3": [
          [
            "C22C3",
            "C32C4"
          ],
          [
            "C22C3",
            "C32N3"
          ],
          [
            "C22C3",
            "C32S3"
          ],
          [
            "C42C3",
            "C32C2"
          ],
          [
            "C42C3",
            "C32N3"
          ],
          [
            "C42C3",
            "C32S3"
          ],
          [
            "N32C3",
            "C32C2"
          ],
          [
            "N32C3",
            "C32C4"
          ],
          [
            "N32C3",
            "C32S3"
          ],
          [
            "S32C3",
            "C32C2"
          ],
          [
            "S32C3",
            "C32C4"
          ],
          [
            "S32C3",
            "C32N3"
          ]
        ],
        "C4": [
          [
            "C32C4",
            "C42C5"
          ],
          [
            "C32C4",
            "C42N4"
          ],
          [
            "C32C4",
            "C42S4"
          ],
          [
            "C52C4",
            "C42C3"
          ],
          [
            "C52C4",
            "C42N4"
          ],
          [
            "C52C4",
            "C42S4"
          ],
          [
            "N42C4",
            "C42C3"
          ],
          [
            "N42C4",
            "C42C5"
          ],
          [
            "N42C4",
            "C42S4"
          ],
          [
            "S42C4",
            "C42C3"
          ],
          [
            "S42C4",
            "C42C5"
          ],
          [
            "S42C4",
            "C42N4"
          ]
        ],
        "C5": [
          [
            "C42C5",
            "C52E_out"
          ],
          [
            "C42C5",
            "C52N5"
          ],
          [
            "C42C5",
            "C52S5"
          ],
          [
            "E_out2C5",
            "C52C4"
          ],
          [
            "E_out2C5",
            "C52N5"
          ],
          [
            "E_out2C5",
            "C52S5"
          ],
          [
            "N52C5",
            "C52C4"
          ],
          [
            "N52C5",
            "C52E_out"
          ],
          [
            "N52C5",
            "C52S5"
          ],
          [
            "S52C5",
            "C52C4"
          ],
          [
            "S52C5",
            "C52E_out"
          ],
          [
            "S52C5",
            "C52N5"
          ]
        ]
      }
    }
  ]
}